setup.cfg
setup.py
nbserve/__init__.py
nbserve/app.py
nbserve/cli.py
nbserve/meta.py
nbserve/nbexporter.py
nbserve.egg-info/PKG-INFO
nbserve.egg-info/SOURCES.txt
nbserve.egg-info/dependency_links.txt
nbserve.egg-info/entry_points.txt
nbserve.egg-info/not-zip-safe
nbserve.egg-info/requires.txt
nbserve.egg-info/top_level.txt