Metadata-Version: 1.0
Name: nbserve
Version: 0.4.1
Summary: UNKNOWN
Home-page: https://github.com/robchambers/nbserve
Author: Rob Chambers
Author-email: rdchambers@gmail.com
License: UNKNOWN
Keywords: jupyter,notebook,flask,server
Platform: UNKNOWN
